{"pageName":"login","pagePath":"login","metaData":{},"componentsTree":{"type":"pageComponent","props":{"componentName":"usr.layouts.SingleFormLayout.SingleFormLayout","componentInstance":"loginFormLayout"},"children":[{"type":"pageComponent","props":{"componentName":"usr.forms.LoginForm.LoginForm","componentInstance":"loginForm","elementProperty":"formArea"}},{"type":"pageComponent","props":{"componentName":"usr.forms.SingleButtonForm.SingleButtonForm","componentInstance":"goToCreateAccount","elementProperty":"bottomArea"}}]}}